pytest_shell/__init__.py
pytest_shell/connection.py
pytest_shell/dialect.py
pytest_shell/fs.py
pytest_shell/shell.py
pytest_shell-0.3.2.dist-info/entry_points.txt
pytest_shell-0.3.2.dist-info/LICENSE
pytest_shell-0.3.2.dist-info/WHEEL
pytest_shell-0.3.2.dist-info/METADATA
pytest_shell-0.3.2.dist-info/RECORD
