Metadata-Version: 2.1
Name: pytest-shell
Version: 0.3.2
Summary: A pytest plugin to help with testing shell scripts / black box commands
Home-page: https://hg.sr.ht/~danmur/pytest-shell
License: MIT
Author: Daniel Murray
Author-email: daniel@darkdisco.net
Requires-Python: >=3.7,<4.0
Classifier: License :: OSI Approved :: MIT License
Classifier: Programming Language :: Python :: 3
Classifier: Programming Language :: Python :: 3.10
Classifier: Programming Language :: Python :: 3.7
Classifier: Programming Language :: Python :: 3.8
Classifier: Programming Language :: Python :: 3.9
Requires-Dist: where (>=1.0.2,<2.0.0)
Project-URL: Changelog, https://hg.sr.ht/~danmur/pytest-shell/browse/CHANGES.rst?rev=tip
Project-URL: Documentation, https://hg.sr.ht/~danmur/pytest-shell/browse/README.rst?rev=tip
Project-URL: Issues, https://todo.sr.ht/~danmur/pytest-shell
Project-URL: Repository, https://hg.sr.ht/~danmur/pytest-shell
